LibcSearcher3/__init__.py
LibcSearcher3/cmd.py
LibcSearcher3/main.py
LibcSearcher3/test.py
LibcSearcher3/utils.py
LibcSearcher3/db/libc.tar.bz2
LibcSearcher3-1.4.0.dist-info/LICENSE
LibcSearcher3-1.4.0.dist-info/METADATA
LibcSearcher3-1.4.0.dist-info/WHEEL
LibcSearcher3-1.4.0.dist-info/entry_points.txt
LibcSearcher3-1.4.0.dist-info/top_level.txt
LibcSearcher3-1.4.0.dist-info/RECORD
