Metadata-Version: 2.1
Name: LibcSearcher3
Version: 1.4.0
Summary: libc offset database searcher
Home-page: https://github.com/Ro0tk1t/LibcSearcher3.git
Author: Ro0tk1t
Author-email: R00tk1t@qq.com
License: UNKNOWN
Platform: UNKNOWN
Requires-Python: >=3.7
